{"url": "https://www.youtube.com/watch?v=g4lJ9mkq7Lw&pp=0gcJCX4JAYcqIYzv", "titulo": "Mensagem 13/09/2020 | Judas 1.17-25 | Pr. Fábio Moreira", "possui_transcricao": true, "transcricao": [{"tStartMs": 2170, "text": "um  dos  com  a  graça  a  paz  do  Senhor  Jesus"}, {"tStartMs": 5500, "text": "Cristo  o  salvador  dos  eleitos  Você  pode"}, {"tStartMs": 9610, "text": "abrir  a  sua  Bíblia  para  a  epístola  de"}, {"tStartMs": 13090, "text": "Judas"}, {"tStartMs": 14220, "text": "in  my  pizza  pequena  só  tem  um  capítulo"}, {"tStartMs": 19400, "text": "Oi  e  o  verso  da  nossa  do  nosso  interesse"}, {"tStartMs": 22070, "text": "hoje  será  a  partir  do  16  17  até  o  25  nós"}, {"tStartMs": 28310, "text": "iremos  concluir  Então  hoje  a  nossa"}, {"tStartMs": 30680, "text": "minissérie"}, {"tStartMs": 32279, "text": "e  na  epístola  de  Judas  mas  antes  de"}, {"tStartMs": 35190, "text": "começarmos  vamos  orar  Senhor  Deus  eu"}, {"tStartMs": 39930, "text": "quero  um"}, {"tStartMs": 41230, "text": "a  reconhecer  o  pai"}, {"tStartMs": 44660, "text": "e  o  teu  grande  amor  por  nós"}, {"tStartMs": 47110, "text": "o  visto  na  cruz  do  Calvário  Quando  o"}, {"tStartMs": 50740, "text": "senhor  Jesus  Cristo  deixou  a  sua  glória"}, {"tStartMs": 52950, "text": "veio  viver  uma  vida  aqui  neste  mundo"}, {"tStartMs": 56190, "text": "comprei  a  justiça  perfeita  e  nosso  lugar"}, {"tStartMs": 59040, "text": "e  por  meio  Deus  do  sangue  dEle  do  sangue"}, {"tStartMs": 62590, "text": "de  Jesus  derramado  nós  temos  acesso  a"}, {"tStartMs": 65620, "text": "tua  presença  Vamos  alterar  o  meu  Deus"}, {"tStartMs": 68560, "text": "porque  esse  plano"}, {"tStartMs": 71060, "text": "se  revela  o  teu  caráter  quem  o  senhor  é"}, {"tStartMs": 74060, "text": "a  tua  sabedoria  tua  bondade  e  a  tua"}, {"tStartMs": 75979, "text": "graça  tua  justiça  e  o  teu  amor  vamos  o"}, {"tStartMs": 80570, "text": "teu  nome  Porque  somente  um  Deus  gracioso"}, {"tStartMs": 83299, "text": "e  misericordioso  iria  buscar  o  perdido"}, {"tStartMs": 87350, "text": "pecador  pai  porque  eu  só  tenho  espírito"}, {"tStartMs": 90950, "text": "nos  visite"}, {"tStartMs": 92409, "text": "o  que  possamos  a  Deus  ter  o  nosso"}, {"tStartMs": 94780, "text": "coração  a  aberto  e  pronto  para  ouvir  a"}, {"tStartMs": 99819, "text": "tua  palavra  e  sermos  edificados  por  ela"}, {"tStartMs": 103509, "text": "Senhor  porque  ela  que  tem  poder  é  o  teu"}, {"tStartMs": 107350, "text": "santo  espírito  agindo  entre  nós  que  nos"}, {"tStartMs": 110350, "text": "convence  o  Deus  da  nossa  realidade  e  nos"}, {"tStartMs": 113649, "text": "aponta  para  a  esperança  que  temos  em"}, {"tStartMs": 116200, "text": "Jesus  Cristo  e  nos  na  sua  obra  consumada"}, {"tStartMs": 118719, "text": "na  cruz  do  Calvário  pedimos  saber  o  Deus"}, {"tStartMs": 122229, "text": "para  aqueles  que  nos  assistem"}, {"tStartMs": 124770, "text": "o  que  o  Senhor  possa  também  falar  o"}, {"tStartMs": 126840, "text": "coração  deles  lembrá-los  a  Deus  a  que  o"}, {"tStartMs": 130979, "text": "senhor  aqui  nos  guarda  que  o  senhor  aqui"}, {"tStartMs": 133319, "text": "nos  impede  de  tropeçar  e  que  o  Senhor"}, {"tStartMs": 136080, "text": "tem  um  plano  maravilhoso  para  nós  na"}, {"tStartMs": 138540, "text": "eternidade  E  aí  nome  de  Jesus  que  eu  oro"}, {"tStartMs": 141269, "text": "e  agradeço  amém"}, {"tStartMs": 144930, "text": "Tá  bom  então  nós  temos  aqui"}, {"tStartMs": 147460, "text": "e  além  do  meu  desafio  de  lidar  com  vento"}, {"tStartMs": 150310, "text": "de  segurar  aqui  a  página  da  Bíblia  o"}, {"tStartMs": 154180, "text": "desafio  de  concluirmos  hoje  uma  carta"}, {"tStartMs": 157180, "text": "especial  a  carta  de  um  homem  chamado"}, {"tStartMs": 159550, "text": "Judas  que  não  é  o  Judas  Iscariotes  mas"}, {"tStartMs": 163270, "text": "sim  é  o  irmão  o  meio-irmão  do  nosso"}, {"tStartMs": 166480, "text": "senhor  Jesus  Cristo  é  irmão  de  Tiago"}, {"tStartMs": 169440, "text": "então  se  você  se  lembra  nós  a  fizemos  a"}, {"tStartMs": 173830, "text": "leitura  e  Judas  então  começa  a  saudar  os"}, {"tStartMs": 177880, "text": "seus  leitores  ele  fala  quem  ele  é  ele"}, {"tStartMs": 180850, "text": "ele  ele  nos  relembra  daquilo  que  nós"}, {"tStartMs": 183430, "text": "somos  em  Cristo  Jesus  nós  somos  amados"}, {"tStartMs": 186730, "text": "pelo  senhor  nós  somos  chamados  somos"}, {"tStartMs": 189310, "text": "também  guardados  em  Jesus  Cristo  e  Então"}, {"tStartMs": 193960, "text": "faz  a  um  desejo  misericórdia  a  paz  e  o"}, {"tStartMs": 198580, "text": "amor  você  sejam  multiplicadas  luz  remete"}, {"tStartMs": 202050, "text": "aquilo  que  todo  verdadeiro  Cristão"}, {"tStartMs": 205260, "text": "desfruta  em"}, {"tStartMs": 207470, "text": "e  em  Cristo  Jesus  e  desfruta  de  uma"}, {"tStartMs": 211130, "text": "misericórdia  abundante  de  uma  paz"}, {"tStartMs": 213350, "text": "abundante  de  um  amor  abundante  Então"}, {"tStartMs": 217430, "text": "logo  em  seguida  ajuda  as  começa  a  nos"}, {"tStartMs": 219170, "text": "mostrar  que  ele  havia  intencionado"}, {"tStartMs": 221960, "text": "Originalmente  escrever  sobre  a  salvação"}, {"tStartMs": 223840, "text": "em  Cristo  Jesus  a  salvação  comum  entre"}, {"tStartMs": 227510, "text": "nós  mas  esse  homem  alguém  guiado  pelo"}, {"tStartMs": 230630, "text": "Espírito  Santo  é  um  homem  pleno  Espírito"}, {"tStartMs": 233720, "text": "Santo  Isso  deve  ser  a  nossa  vida  comum"}, {"tStartMs": 236470, "text": "todos  nós  cristãos  devemos  ser  a  marcado"}, {"tStartMs": 241430, "text": "sou  uma  vida  evidenciando  que  somos"}, {"tStartMs": 244190, "text": "controlados  pelo  Espírito  uma  vida  cheia"}, {"tStartMs": 247100, "text": "no  espírito  dele  então  sensível  a  voz  do"}, {"tStartMs": 250370, "text": "Espírito  entendendo  que  havia  uma"}, {"tStartMs": 252650, "text": "mudança  de  tema  queria  abordar  ele  então"}, {"tStartMs": 256220, "text": "começa  a  tratar  agora  da  fé  que  nós"}, {"tStartMs": 260000, "text": "temos  que  batalhar"}, {"tStartMs": 262500, "text": "e  assim  então  interesse  de  Judas  de  que"}, {"tStartMs": 266070, "text": "a  nós  devemos  diligentemente  batalhar"}, {"tStartMs": 271410, "text": "pela  fé  que  uma  vez  por  todas  foi"}, {"tStartMs": 274350, "text": "entregue  aos  santos"}, {"tStartMs": 276340, "text": "e  ele  então  começa  a  compreender  aqui"}, {"tStartMs": 278770, "text": "dentro  da  igreja  havia  um  pessoas  que"}, {"tStartMs": 281800, "text": "dissimuladamente  há  penetraram  e  que  o"}, {"tStartMs": 285490, "text": "seu  interesse  era  desviar  a  sua  atenção"}, {"tStartMs": 288910, "text": "do  Evangelho  desviar  a  sua  atenção  a  da"}, {"tStartMs": 293889, "text": "mensagem  do  Evangelho  da  Verdade  da"}, {"tStartMs": 296889, "text": "escritura  da  revelação  de  Deus  da  pessoa"}, {"tStartMs": 299860, "text": "de  Jesus  Cristo  da  obra  dele"}, {"tStartMs": 302680, "text": "e  ele  então  começa  a  escrever  essas"}, {"tStartMs": 304990, "text": "coisas  primeiramente  para  o  seu  público"}, {"tStartMs": 307449, "text": "primário  e  depois  ao  longo  da  história"}, {"tStartMs": 309870, "text": "até  nós  aqui  2021"}, {"tStartMs": 314020, "text": "o  que  Judas  então  começa  a  mostrar  para"}, {"tStartMs": 317860, "text": "nós  para  os  seus  primeiros  leitores  que"}, {"tStartMs": 321069, "text": "a  um  juízo  que  Deus  é  um  Deus  justo  e  em"}, {"tStartMs": 324879, "text": "sua  justiça  ele  vai  lidar  com  juízo"}, {"tStartMs": 327039, "text": "então  ele  começa  a  mostrar  para  nós  aqui"}, {"tStartMs": 328990, "text": "a  três  exemplos  no  antigo  testamento"}, {"tStartMs": 331740, "text": "sobre  a  justiça  de  Deus  que  ele  aplica  a"}, {"tStartMs": 335409, "text": "condenação  e  aplico  juízo  para  algum"}, {"tStartMs": 338710, "text": "alguns  é  tipos  de  pessoas  então  começa  a"}, {"tStartMs": 343389, "text": "falando  sobre  o  próprio  Israel  a"}, {"tStartMs": 345669, "text": "incredulidade  algo  complicado  Deus  havia"}, {"tStartMs": 348759, "text": "libertado  o  Israel  como  uma  poderosa  e"}, {"tStartMs": 351639, "text": "quando  Israel  teve  aí  a  não  o  seu"}, {"tStartMs": 355000, "text": "primeiro  a  momento  de  provação  mas  sim"}, {"tStartMs": 360430, "text": "quando  eles  recebem  a  ordem  de  espiar  a"}, {"tStartMs": 362680, "text": "terra  porém  eles  contemplam  o  problema"}, {"tStartMs": 366360, "text": "os  10  espias"}, {"tStartMs": 369240, "text": "e  consegue  enxergar  que  há  mais"}, {"tStartMs": 371699, "text": "dificuldades  e  tira  os  olhos  da  Graça  do"}, {"tStartMs": 375389, "text": "Senhor"}, {"tStartMs": 377249, "text": "se  esquecem  de  que  foram  libertados  Por"}, {"tStartMs": 380789, "text": "Um  Deus  poderoso  e  que  esse  Deus  não"}, {"tStartMs": 382559, "text": "falha"}, {"tStartMs": 384340, "text": "a  e  começa  então  a  entender  que  é  um"}, {"tStartMs": 387070, "text": "problema  Seríssimo  nós  não  podemos"}, {"tStartMs": 389470, "text": "entrar  naquela  terra"}, {"tStartMs": 391340, "text": "que  são  gigantes  nós  somos  como"}, {"tStartMs": 394070, "text": "gafanhotos"}, {"tStartMs": 395849, "text": "nós  estamos  fadados"}, {"tStartMs": 398260, "text": "e  a  sermos  derrotados  e  conquistados  mas"}, {"tStartMs": 402010, "text": "Deus  levanta  ele  dois  homens  um  da  tribo"}, {"tStartMs": 404230, "text": "de  Judá  e  um  da  Tribo  de  Efraim"}, {"tStartMs": 406900, "text": "o  Josué  e  Calebe  e  Calebe  l"}, {"tStartMs": 410910, "text": "o  novo  40  anos  novo  o  menino"}, {"tStartMs": 416000, "text": "e  faz  amizade"}, {"tStartMs": 418720, "text": "e  ele  então  Com  os  Olhos  da  Fé"}, {"tStartMs": 422270, "text": "e  olhando  para  as  promessas  de  um  Deus"}, {"tStartMs": 425210, "text": "que  não  falha  ele  encoraja  aquelas"}, {"tStartMs": 428630, "text": "pessoas  mas  infelizmente  a  incredulidade"}, {"tStartMs": 431800, "text": "é  um  perigo  aquela  geração  toda  de  vinte"}, {"tStartMs": 436790, "text": "anos  para  cima  foi  morta  ao  longo  da  sua"}, {"tStartMs": 439820, "text": "jornada  para  a  terra  prometida  depois"}, {"tStartMs": 442850, "text": "ele  nos  lembra  sobre  os  anjos  os  anjos"}, {"tStartMs": 445970, "text": "que  ficaram  insatisfeitos  com  a  sua"}, {"tStartMs": 448550, "text": "condição  que  Deus  havia  dado  para  eles"}, {"tStartMs": 452710, "text": "e  eles  então  fica  Bela  outro  senhor"}, {"tStartMs": 455370, "text": "contra  o  plano  do  senhor  e  o  Senhor"}, {"tStartMs": 458260, "text": "então  os  expulsa  da  sua  presença  e"}, {"tStartMs": 462040, "text": "depois  fomos  lembrados  do  pecado  da"}, {"tStartMs": 464470, "text": "imoralidade  então  o  pecado  da"}, {"tStartMs": 467050, "text": "incredulidade  um  pecado  da  rebelião  e  o"}, {"tStartMs": 471370, "text": "pecado  da  imoralidade  e  ele  então  se"}, {"tStartMs": 475690, "text": "lembra  de  Sodoma  e  Gomorra  e  de  duas"}, {"tStartMs": 478360, "text": "cidades  circunvizinhas"}, {"tStartMs": 480620, "text": "e  onde  a  imoralidade  um  estilo  de  vida"}, {"tStartMs": 483110, "text": "pecaminoso  voltado  para  o  hedonismo"}, {"tStartMs": 486199, "text": "voltado  para  os  seus  próprios  Prazeres"}, {"tStartMs": 489400, "text": "egocêntricos"}, {"tStartMs": 491380, "text": "a  Deus  então  trouxe  juízo  para  aquela"}, {"tStartMs": 494290, "text": "cidades"}, {"tStartMs": 495449, "text": "e  depois  ele  nos  relembra  e  começa"}, {"tStartMs": 498809, "text": "também  a  fazer  uma  descrição  de  quem  são"}, {"tStartMs": 504059, "text": "aqueles  homens"}, {"tStartMs": 507330, "text": "bom  então  juntas  está  aqui  nos  ajudando"}, {"tStartMs": 509699, "text": "e  mostrando  para  nós"}, {"tStartMs": 512140, "text": "e  quem  são  aquelas  pessoas  como"}, {"tStartMs": 515530, "text": "identificá-los"}, {"tStartMs": 517110, "text": "e  nem  chegamos  então"}, {"tStartMs": 520200, "text": "e  no  verso  17  eu  peço  que  você  abre"}, {"tStartMs": 523020, "text": "então  A  sua  Bíblia  no  verso  17"}, {"tStartMs": 528110, "text": "a  e  agora  então  ele  vai  passar  a  fazer"}, {"tStartMs": 530480, "text": "algumas  injunções"}, {"tStartMs": 533150, "text": "e  para  os  seus  leitores  primários"}, {"tStartMs": 537240, "text": "o  desafio  texto  voz  porém  amados"}, {"tStartMs": 540589, "text": "lembrai-vos  das  palavras  anteriormente"}, {"tStartMs": 543270, "text": "proferidas  pelos  apóstolos  de  Nosso"}, {"tStartMs": 545250, "text": "Senhor  Jesus  Cristo  os  quais  os  diziam"}, {"tStartMs": 548459, "text": "no  último  tempo  haverá  escarnecedores"}, {"tStartMs": 550520, "text": "andando  segundo  a  sozinho  pelas  paixões"}, {"tStartMs": 553520, "text": "são  esses  que  promovem  divisões  sensuais"}, {"tStartMs": 557370, "text": "que  não  tem  um  espírito  voz  porém  amados"}, {"tStartMs": 561240, "text": "edificando-vos  na  vossa  fé  santíssima"}, {"tStartMs": 563700, "text": "orando  no  Espírito  Santo  guardai-vos  no"}, {"tStartMs": 567209, "text": "amor  de  Deus  esperando  a  misericórdia  de"}, {"tStartMs": 570089, "text": "Nosso  Senhor  Jesus  Cristo  para  a  vida"}, {"tStartMs": 572339, "text": "eterna  e  compadecei-vos  de  alguns  que"}, {"tStartMs": 576000, "text": "estão  na  dúvida  só  vários  arrebatando-os"}, {"tStartMs": 580020, "text": "do  fogo  quanto  a  outros  sede  também"}, {"tStartMs": 583560, "text": "compassivo  sem  temor  de  testando  até  a"}, {"tStartMs": 586709, "text": "roupa  contaminada  pela  carne"}, {"tStartMs": 589350, "text": "e  ora  aquele  que  é  poderoso  para  vos"}, {"tStartMs": 592470, "text": "guardar  de  tropeços  e  para  vos"}, {"tStartMs": 594390, "text": "apresentar  com  exultação  imaculados"}, {"tStartMs": 596780, "text": "Diante  da  sua  glória  ao  único  Deus  nosso"}, {"tStartMs": 600270, "text": "salvador  mediante  Jesus  Cristo  senhor"}, {"tStartMs": 602790, "text": "nosso  Lu  glória  majestade  império  e"}, {"tStartMs": 607290, "text": "soberania  antes  de  todas  as  eras  e  agora"}, {"tStartMs": 609750, "text": "e  por  todos  os  séculos  amém"}, {"tStartMs": 615440, "text": "a  ajuda  de  escravos  epístola  para"}, {"tStartMs": 617510, "text": "alertar  a  igreja  sobre  falsos  ensinos  a"}, {"tStartMs": 620180, "text": "igreja  então  desfrutava  de  um  tempo"}, {"tStartMs": 621770, "text": "tranquilo  e  havia  baixado  a  guarda"}, {"tStartMs": 624490, "text": "juntas  então  ficou  Sentra  não  sobre"}, {"tStartMs": 627620, "text": "aquilo  que  as  pessoas  estão  ensinando"}, {"tStartMs": 631740, "text": "e  você  vai  legal  se  você  pudesse"}, {"tStartMs": 633450, "text": "acompanhar  né"}, {"tStartMs": 637010, "text": "e  eles  estão  obviamente  preocupados  com"}, {"tStartMs": 640220, "text": "esses  falsos  falsos  behavioristas  estão"}, {"tStartMs": 644210, "text": "atraindo  outros  cristãos  para  o  seu"}, {"tStartMs": 646820, "text": "próprio  estilo  de  vida  pecaminoso"}, {"tStartMs": 657430, "text": "e  são  pessoas  então  que  receberam  a"}, {"tStartMs": 659860, "text": "verdade  rejeitaram  a  verdade"}, {"tStartMs": 663060, "text": "ridicularizaram  a  verdade  e"}, {"tStartMs": 665440, "text": "eventualmente  tentaram  substituir  a"}, {"tStartMs": 669310, "text": "verdade"}, {"tStartMs": 670920, "text": "Oi  hoje  é  uma  grande  necessidade  de"}, {"tStartMs": 673050, "text": "darmos  ouvidos  às  palavras  de  Judas  e"}, {"tStartMs": 675029, "text": "batalhar  diligentemente  pela  fé  que  uma"}, {"tStartMs": 677850, "text": "vez  por  todas  foi  entregue  aos  santos"}, {"tStartMs": 680540, "text": "portanto  irmãos  a  uma  batalha  a  uma  luta"}, {"tStartMs": 684600, "text": "pela  fé  uma  luta  para  preservar  e"}, {"tStartMs": 687839, "text": "transmitir  o  que  nos  foi  entregue"}, {"tStartMs": 691290, "text": "e  como  nós  então  podemos"}, {"tStartMs": 694339, "text": "e  como  crentes  batalhar  pela  verdade"}, {"tStartMs": 697519, "text": "para  que  possamos  ser  vitoriosos"}, {"tStartMs": 700440, "text": "e  como  podemos  então  aplicar"}, {"tStartMs": 702630, "text": "pessoalmente  advertência  contra  a"}, {"tStartMs": 705360, "text": "apostasia  em  relação  as  nossas  próprias"}, {"tStartMs": 707640, "text": "vidas  e  Ministérios  não  é  suficiente"}, {"tStartMs": 711780, "text": "apenas  você  falar  identificar  que  há"}, {"tStartMs": 714210, "text": "pessoas  que  têm  um  estilo  de  vida"}, {"tStartMs": 716130, "text": "pecaminoso  que  são  voltados  para  uma"}, {"tStartMs": 718620, "text": "vida  a  para  satisfazer  a  carne"}, {"tStartMs": 724209, "text": "não  é  necessário  então  que  sejamos"}, {"tStartMs": 726459, "text": "instruídos  e  como  devemos  lidar  com  a"}, {"tStartMs": 730029, "text": "realidade  é  essa"}, {"tStartMs": 732030, "text": "e  como  temos  que  nos  comportaram  Qual  o"}, {"tStartMs": 736050, "text": "nosso  papel  frente  a  uma  realidade  que"}, {"tStartMs": 738090, "text": "ao  longo  de  toda  a  história  se  tornou"}, {"tStartMs": 741920, "text": "verdade  então  os  cristãos  que  são"}, {"tStartMs": 746100, "text": "guardados  pelo  poder  de  Deus  são"}, {"tStartMs": 748110, "text": "chamados  a  crescer  em  maturidade"}, {"tStartMs": 749790, "text": "espiritual  zelando  pela  fé  verdadeira"}, {"tStartMs": 753330, "text": "para  que  o  louvor  da  para  o  louvor  da"}, {"tStartMs": 757410, "text": "Glória  de  Deus  então  em  primeiro  lugar"}, {"tStartMs": 761090, "text": "lembre-se  da  palavra  de  Cristo"}, {"tStartMs": 766240, "text": "bom  então  juntas  está  dizendo  verso  17"}, {"tStartMs": 770440, "text": "voz  porém  amados  lembrai-vos  das"}, {"tStartMs": 772930, "text": "palavras  anteriormente  proferidas  pelos"}, {"tStartMs": 777250, "text": "Apóstolos  aqui  lembrar  não  é  um  convite"}, {"tStartMs": 779950, "text": "apenas  trazer  à  memória  mas  uma"}, {"tStartMs": 782740, "text": "lembrança  que  vai  impactar  você  que  vai"}, {"tStartMs": 785709, "text": "levar  você  a  ter  um  comportamento  vai"}, {"tStartMs": 788880, "text": "atuar  na  sua  vontade"}, {"tStartMs": 793160, "text": "e  não  é  apenas  um  convite  mas  é  algo  que"}, {"tStartMs": 796339, "text": "vai  mudar  o  seu  comportamento"}, {"tStartMs": 800579, "text": "com  a  presença  dos  sócios  Mestres  é"}, {"tStartMs": 802949, "text": "certa  Veja  por  meio  dos  seus  Apóstolos"}, {"tStartMs": 806970, "text": "Jesus  avisou  da  presença  dessas  pessoas"}, {"tStartMs": 809569, "text": "Mateus  7:15  acautelai-vos  dos  falsos"}, {"tStartMs": 812959, "text": "profetas  que  se  vos  apresentam"}, {"tStartMs": 815579, "text": "disfarçados  em  ovelhas  Jesus  Cristo  já"}, {"tStartMs": 819509, "text": "havia  informado  isso  e  ele  o  Faça  no"}, {"tStartMs": 822720, "text": "maior  sermão  que  essa  terra  já  ouviu  no"}, {"tStartMs": 825089, "text": "sermão  do  Monte"}, {"tStartMs": 826529, "text": "e  ele  está  dizendo  ali  nem  todo  aquele"}, {"tStartMs": 829529, "text": "que  diz  senhor  senhor  entrará  no  reino"}, {"tStartMs": 831629, "text": "dos  céus  bem  todo  aquele  que  a  diz  que"}, {"tStartMs": 835199, "text": "em  teu  nome  o  senhor  expulsa  os  demônios"}, {"tStartMs": 837649, "text": "e  em  teu  nome  fizemos  tantas  coisas"}, {"tStartMs": 840410, "text": "Jesus  Cristo  vai  se  virar  para  eles  de"}, {"tStartMs": 842759, "text": "dizer  apartai-vos  de  mim  Não  vos  conheço"}, {"tStartMs": 847750, "text": "em  Mateus  24  Jesus  ainda  fala"}, {"tStartMs": 851010, "text": "levantar-se-ão  muitos  falsos  profetas  e"}, {"tStartMs": 854170, "text": "enganarão  a  muitos  Então  por  meio  de"}, {"tStartMs": 858070, "text": "seus  Apóstolos  o  nosso  senhor"}, {"tStartMs": 861500, "text": "e  ele  avisou  que  falsos  Mestres  viriam"}, {"tStartMs": 864520, "text": "na  verdade  eles  nos  avisaram  que  ficar"}, {"tStartMs": 867620, "text": "vencedores  apareceriam  especificamente"}, {"tStartMs": 870620, "text": "os  últimos  tempos"}, {"tStartMs": 873050, "text": "a  ver  jatos  20  de  29  a  30  eu  sei  que"}, {"tStartMs": 877250, "text": "depois  da  minha  partida  entre  vós"}, {"tStartMs": 879580, "text": "penetraram  Lobos  Vorazes  que  não"}, {"tStartMs": 881990, "text": "pouparão  o  rebanho  e  que  dentre  vós"}, {"tStartMs": 884570, "text": "mesmos  se  levantarão  homens  falando"}, {"tStartMs": 887660, "text": "coisas  pervertidas  para  arrastar  os"}, {"tStartMs": 890839, "text": "discípulos  atrás  dele  o  contexto  é"}, {"tStartMs": 893450, "text": "quando  o  Paulo  está  a  saindo  de  Éfeso"}, {"tStartMs": 896320, "text": "ele  então  está  informando  está  a"}, {"tStartMs": 899470, "text": "ensinando  e  mostrando  para  aquela  igreja"}, {"tStartMs": 902500, "text": "irão  se  levantar  até  mesmo  entre  vocês"}, {"tStartMs": 905950, "text": "homens  que  irão  perverter  a  verdade  do"}, {"tStartMs": 910220, "text": "Evangelho"}, {"tStartMs": 913710, "text": "a  segunda  Pedro  2  de  12  assim  como  no"}, {"tStartMs": 917460, "text": "meio  do  povo  surgiram  falsos  profetas"}, {"tStartMs": 919520, "text": "assim  também  haverá  entre  vós  falsos"}, {"tStartMs": 922380, "text": "Mestres  os  quais  introduziram"}, {"tStartMs": 925170, "text": "dissimuladamente  heresias  destruidoras"}, {"tStartMs": 927590, "text": "até  o  ponto  de  renegar  e  o  soberano"}, {"tStartMs": 930510, "text": "senhor  que  os  resgatou  trazendo  sobre  si"}, {"tStartMs": 933480, "text": "mesmos  repentina  destruição  e  muitos"}, {"tStartMs": 937290, "text": "seguirão  as  suas  práticas  libertinas  e"}, {"tStartMs": 939600, "text": "por  causa  deles  será  infamado  o  caminho"}, {"tStartMs": 942620, "text": "da  Verdade  portanto  a  igreja  não  deve  se"}, {"tStartMs": 946080, "text": "surpreender  com  a  inclusão  dessas"}, {"tStartMs": 948630, "text": "pessoas"}, {"tStartMs": 949830, "text": "é  mas  deve  se  deve  estar  preparada  para"}, {"tStartMs": 953190, "text": "se  defender  da  presença  insidiosa  desses"}, {"tStartMs": 958350, "text": "intrusos"}, {"tStartMs": 960310, "text": "e  a  imagem  dos  falsos  Mestres  ela  é"}, {"tStartMs": 963220, "text": "Clara  veja"}, {"tStartMs": 966100, "text": "e  eles  são  escarnecedores  aqui  juntas"}, {"tStartMs": 969639, "text": "está  informando  que  não  são  apenas"}, {"tStartMs": 972370, "text": "pessoas  que  vão  zombar  da  doutrina  que"}, {"tStartMs": 976569, "text": "vão  tirar  onda  daquilo  que  a  Nós  cremos"}, {"tStartMs": 981540, "text": "daquilo  que  nós  consideramos  entendemos"}, {"tStartMs": 984370, "text": "que  é  uma  verdade  perene  mas  são  pessoas"}, {"tStartMs": 987490, "text": "que  são  os  dias  a  revelação"}, {"tStartMs": 991089, "text": "é  só  pessoas  que  são  indiferentes  aquilo"}, {"tStartMs": 995139, "text": "que  Jesus  Cristo  fez"}, {"tStartMs": 997260, "text": "e  irão  estes  carnê  ser  dessas  verdades"}, {"tStartMs": 1004000, "text": "e  eles  serão  sensuais"}, {"tStartMs": 1006920, "text": "é  isso  quer  dizer  que  esses  homens  andam"}, {"tStartMs": 1010430, "text": "de  acordo  com  suas  próprias  paixões"}, {"tStartMs": 1013510, "text": "ímpias  a  sua  própria  Luxúria  veja  é"}, {"tStartMs": 1017209, "text": "quando  o  verso  16  Judas  acrescenta  que"}, {"tStartMs": 1020060, "text": "seguindo  após  e  sendo  controlados  por"}, {"tStartMs": 1023660, "text": "esse  desejo  incontrolável"}, {"tStartMs": 1026890, "text": "e  eles  perseguem  qualquer  coisa  que"}, {"tStartMs": 1029410, "text": "agrada  seus  desejos  egoístas"}, {"tStartMs": 1033319, "text": "e  São  pessoas  que  criam  divisões  dentro"}, {"tStartMs": 1036380, "text": "do  rebanho"}, {"tStartMs": 1038819, "text": "e  isso  é  uma  estratégia  de  satanás"}, {"tStartMs": 1040740, "text": "Satanás  adora  dividir"}, {"tStartMs": 1043260, "text": "é  a  forma  como  Satanás  lida  e  que  a"}, {"tStartMs": 1046740, "text": "minar  a  igreja"}, {"tStartMs": 1049070, "text": "a  igreja  do  Senhor  Jesus  Cristo  em"}, {"tStartMs": 1052160, "text": "filtrando  pessoas  e  usando  expedients"}, {"tStartMs": 1056210, "text": "para  que  a  divisão  possa  ocorrer  eu"}, {"tStartMs": 1061310, "text": "comentei  com  vocês  aqui  domingo  passado"}, {"tStartMs": 1063080, "text": "de  uma  série  que  eu  venho  assistindo  e"}, {"tStartMs": 1066980, "text": "parte  da  estratégia  de  derrotar  o"}, {"tStartMs": 1069800, "text": "inimigo  é  fazer  com  que  pessoas"}, {"tStartMs": 1072310, "text": "infiltrem  naquele  exército  naquela"}, {"tStartMs": 1076130, "text": "comunidade  e  fazer  então  com  que  a"}, {"tStartMs": 1078980, "text": "divisão  a  briga  interna  seja  uma"}, {"tStartMs": 1082100, "text": "realidade  é  uma  forma  de  enfraquecer"}, {"tStartMs": 1085970, "text": "e  o  adversário  E  é  isso  que  Satanás  faz"}, {"tStartMs": 1088910, "text": "por  meio  desses  homens"}, {"tStartMs": 1091910, "text": "e  portanto  meu  irmão  minha  irmã  dentro"}, {"tStartMs": 1094160, "text": "da  igreja  quando  você  for  submetido  ou"}, {"tStartMs": 1096380, "text": "você  com  discernimento  compreender  que"}, {"tStartMs": 1101510, "text": "algum  irmão  está  usando  uma  linguagem"}, {"tStartMs": 1105460, "text": "que  venha  a  criar  alguma  divisão  aqui"}, {"tStartMs": 1110410, "text": "você  seja  madura  espiritualmente  Resort"}, {"tStartMs": 1115940, "text": "esse  irmão  em  amor"}, {"tStartMs": 1118740, "text": "Olá  seja  gracioso  com  as  suas  palavras"}, {"tStartMs": 1121550, "text": "mostrando  a  ele  que  aquele  tipo  de"}, {"tStartMs": 1123540, "text": "comentário"}, {"tStartMs": 1125120, "text": "Esse  é  o  expediente  para  causar  divisão"}, {"tStartMs": 1128380, "text": "e  divisão  é  estratégia  de  satanás  e  dos"}, {"tStartMs": 1132650, "text": "seus  falsos  Mestres  e"}, {"tStartMs": 1135080, "text": "e  eles  não  têm  o  espírito  isso  é  muito"}, {"tStartMs": 1138440, "text": "sério  isso  quer  dizer  que  são  pessoas"}, {"tStartMs": 1140600, "text": "que  não  foram  regenerados  São  pessoas"}, {"tStartMs": 1143480, "text": "que  não  foram  a  salvas  pelo  Senhor  Jesus"}, {"tStartMs": 1149140, "text": "estão  perdidas  não  tenho  o  espírito  e  se"}, {"tStartMs": 1152929, "text": "alguém  não  tem  o  espírito  de  Cristo  esse"}, {"tStartMs": 1156019, "text": "não  pertence  a  ele"}, {"tStartMs": 1158230, "text": "e  eles  podem  até  mesmo  reivindicar  a"}, {"tStartMs": 1160720, "text": "Cristo  mas  não  conhecem  não  possui  um"}, {"tStartMs": 1164860, "text": "relacionamento  pessoal  com  o  senhor"}, {"tStartMs": 1167810, "text": "e  são  fraudes  espirituais  fraudes"}, {"tStartMs": 1170390, "text": "religiosas  como  título  um  16  de  eles"}, {"tStartMs": 1173510, "text": "afirmam  conhecer  a  Deus  mas  o  negão"}, {"tStartMs": 1177130, "text": "pelas  suas  obras"}, {"tStartMs": 1180269, "text": "em  segundo  lugar  permaneça  no  amor  de"}, {"tStartMs": 1184859, "text": "Deus  veja  crença  na  palavra  de  Deus"}, {"tStartMs": 1189670, "text": "e  nós  somos  aqui  admoestados  a  edificar"}, {"tStartMs": 1194320, "text": "edificar  mus  na  fé  santíssima  a  fé  que  o"}, {"tStartMs": 1199000, "text": "de  uma  vez  por  todas  foi  entregue  aos"}, {"tStartMs": 1200860, "text": "santos  o  que  isso  quer  dizer  que  a  fé  é"}, {"tStartMs": 1203860, "text": "o  fundamento  sobre  o  qual  se  deve"}, {"tStartMs": 1206200, "text": "edificar  não  é  aquela  fé  Salvadora  não  é"}, {"tStartMs": 1209740, "text": "pela  fé  que  você  recebe  o  espírito  santo"}, {"tStartMs": 1212350, "text": "e  coloca  então  a  sua  confiança  na  obra"}, {"tStartMs": 1215980, "text": "do  senhor  Jesus  Cristo  mas  aquele"}, {"tStartMs": 1218410, "text": "conjunto  de  verdade  são  aquelas  aquele"}, {"tStartMs": 1222250, "text": "conjunto  de  valores  e  de  doutrinas  pelas"}, {"tStartMs": 1225940, "text": "quais  Nós  cremos  pelas  quais  recebemos"}, {"tStartMs": 1228580, "text": "por  meio  de  Revelação  divina"}, {"tStartMs": 1231309, "text": "e  o  evangelho  de  Cristo"}, {"tStartMs": 1235490, "text": "e  edificados  sobre  o  fundamento  dos"}, {"tStartMs": 1237800, "text": "Apóstolos  e  profetas  sendo  ele  mesmo"}, {"tStartMs": 1240500, "text": "Cristo  Jesus  a  Pedra  Angular"}, {"tStartMs": 1244370, "text": "e  portanto  a  nossa  fé  a  deve  ser"}, {"tStartMs": 1248210, "text": "edificada  na  pessoa  e  na  obra  de  Jesus"}, {"tStartMs": 1251110, "text": "naquilo  que  o  os  profetas  e  os  apóstolos"}, {"tStartMs": 1254570, "text": "ensinaram  Ou  seja  a  nossa  fé  deve  ser"}, {"tStartMs": 1258050, "text": "edificada  na  palavra  de  Deus"}, {"tStartMs": 1261980, "text": "ó  e  aqui  um  cuidado  para  com  aqueles  que"}, {"tStartMs": 1265250, "text": "gostam  de  uma  uma  literatura  secular  eu"}, {"tStartMs": 1269179, "text": "não  estou  incentivando  você  ou  aliás"}, {"tStartMs": 1271990, "text": "desde  estimulando  você  a  ler  outras"}, {"tStartMs": 1274850, "text": "coisas  mas  seja  Prudente  naquilo  que"}, {"tStartMs": 1278990, "text": "você  lê  a  palavra  de  Deus  é  o  livro"}, {"tStartMs": 1282380, "text": "perfeito  inspirado  por  ele  infalível  E  é"}, {"tStartMs": 1286250, "text": "verdade  eterna"}, {"tStartMs": 1288110, "text": "se  você  deve  fazer  uso  de  outros  livros"}, {"tStartMs": 1291160, "text": "Mas  faça  com  a  discernimento  pergunte"}, {"tStartMs": 1296210, "text": "para  alguém  se  já  leu  aquele  livro  se"}, {"tStartMs": 1298670, "text": "tem  boas  indicações  de  livros"}, {"tStartMs": 1301860, "text": "é  mas  cuidado  porque  Infelizmente  o  que"}, {"tStartMs": 1305700, "text": "nós  temos  no  mercado"}, {"tStartMs": 1308370, "text": "e  são  coisas  preciosas  e  lixo"}, {"tStartMs": 1312540, "text": "e  o  que  nós  temos  nos  canais  de"}, {"tStartMs": 1316050, "text": "comunicação  digital  nós  temos  coisas"}, {"tStartMs": 1318300, "text": "preciosas  mas  infelizmente  Também  temos"}, {"tStartMs": 1321450, "text": "muito  lixo"}, {"tStartMs": 1323520, "text": "e  portanto  a  sua  fé  deve  ser  edificada"}, {"tStartMs": 1326280, "text": "na  palavra  de  Deus  a  sua  fé  deve  ser"}, {"tStartMs": 1329610, "text": "edificada  nas  mensagens  que  você  ouve"}, {"tStartMs": 1332520, "text": "dessa  igreja  EA  sua  igreja  tem  um"}, {"tStartMs": 1335250, "text": "púlpito  forte"}, {"tStartMs": 1336780, "text": "eu  não  acho  a  construção  sua  concepção"}, {"tStartMs": 1339840, "text": "porque  ele  é  de  MDF"}, {"tStartMs": 1343170, "text": "é  mas  Deus  nos  deu  a  graça  de  termos"}, {"tStartMs": 1346470, "text": "homens  que  amam  a  palavra  do  senhor  que"}, {"tStartMs": 1350730, "text": "tem  um  compromisso  sério  com  o  senhor"}, {"tStartMs": 1353000, "text": "que  se  submetem  a  esse  senhor"}, {"tStartMs": 1356429, "text": "O  que  é  segurança  para  você  então  quando"}, {"tStartMs": 1359639, "text": "você  é  instruído  quando  você  é"}, {"tStartMs": 1361730, "text": "pastoreado"}, {"tStartMs": 1363149, "text": "eu  deposito"}, {"tStartMs": 1365620, "text": "a  Cristo  e  seu  evangelho  encontrado  nas"}, {"tStartMs": 1368559, "text": "escrituras  são  o  nosso  alicerce  Portanto"}, {"tStartMs": 1373390, "text": "o  nosso  alicerce  não  são  os  dogmas  não"}, {"tStartMs": 1376750, "text": "são  os  credos  mas  é  unicamente  a  palavra"}, {"tStartMs": 1381220, "text": "do  senhor"}, {"tStartMs": 1383380, "text": "e  ore  no  espírito  e  horário  Espírito"}, {"tStartMs": 1387130, "text": "Santo  é  o  segundo  passo  de  nossa"}, {"tStartMs": 1389620, "text": "estratégia  espiritual  para  a  saúde"}, {"tStartMs": 1391240, "text": "espiritual  essa  expressão  não  se  refere"}, {"tStartMs": 1393850, "text": "e  falar  em  línguas"}, {"tStartMs": 1395890, "text": "em  línguas  estranhas  mais  orar  por"}, {"tStartMs": 1399220, "text": "aquilo  que  é  coerente  com  a  vontade  e  o"}, {"tStartMs": 1402250, "text": "desejo  do  Espírito  Santo  horário  então"}, {"tStartMs": 1405580, "text": "no  espírito  significa  orar  sobre  sob  a"}, {"tStartMs": 1408490, "text": "influência  do  espírito  e  com  a  sua  ajuda"}, {"tStartMs": 1411720, "text": "o  espírito  Então  meus  irmãos  é  atmosfera"}, {"tStartMs": 1414910, "text": "da  vida  dos  cristãos  E  como  eles  vivem"}, {"tStartMs": 1418270, "text": "no  espírito  a  graça  será  dada  para"}, {"tStartMs": 1420910, "text": "vigiar  e  o  poder  para  continuar  em"}, {"tStartMs": 1424060, "text": "oração"}, {"tStartMs": 1425149, "text": "é  a  vida  do  crente  deve  ser  uma  vida"}, {"tStartMs": 1427460, "text": "caracterizada"}, {"tStartMs": 1430970, "text": "e  por  algo  controlado  e  esse  controle"}, {"tStartMs": 1435169, "text": "deve  ser  o  Espírito  Santo"}, {"tStartMs": 1438640, "text": "eu  não  falei  Efésios  Capítulo  51  Cheios"}, {"tStartMs": 1443080, "text": "do  Espírito  E  como  que  alguém  pode  ser"}, {"tStartMs": 1446170, "text": "cheio  do  espírito"}, {"tStartMs": 1447940, "text": "e  é  alguém  tão  que  de  bruxa  no"}, {"tStartMs": 1451389, "text": "conhecimento  da  escritura  buscando"}, {"tStartMs": 1454509, "text": "conhecer  mais  mais  de  Jesus"}, {"tStartMs": 1456920, "text": "e  é  alguém  que  tem  uma  vida  de  oração  e"}, {"tStartMs": 1460580, "text": "oração  implica  Independência  alguém  tão"}, {"tStartMs": 1463460, "text": "que  reconhece  que  precisa  depender  do"}, {"tStartMs": 1466100, "text": "senhor  é  alguém  que  possui  e  tem  a"}, {"tStartMs": 1469670, "text": "disciplina  de  constantemente  diariamente"}, {"tStartMs": 1473740, "text": "confessar  os  seus  pecados"}, {"tStartMs": 1477779, "text": "é  uma  vida  cheia  do  espírito"}, {"tStartMs": 1480580, "text": "e  é  uma  marca  do  Cristão  portanto  orar"}, {"tStartMs": 1484779, "text": "no  espírito  essa  marca  distintiva  de  um"}, {"tStartMs": 1489190, "text": "verdadeiro  Cristão  isso  faz  é  uma"}, {"tStartMs": 1493179, "text": "antítese  contra  os  falsos  Mestres  Judas"}, {"tStartMs": 1497799, "text": "diz  que  eles  não  tem  espírito"}, {"tStartMs": 1500150, "text": "e  o  crente  regenerado  ele  possui  o"}, {"tStartMs": 1504050, "text": "espírito  santo  o  espírito  santo  habita"}, {"tStartMs": 1506840, "text": "nele"}, {"tStartMs": 1507940, "text": "e  ele  deve  ser  então  Cheio  do  Espírito"}, {"tStartMs": 1511019, "text": "controlado  pelo  Espírito  então  ele  vai"}, {"tStartMs": 1513909, "text": "experimentar  essa  vida  no  espírito  essa"}, {"tStartMs": 1516610, "text": "vida  de  oração"}, {"tStartMs": 1519130, "text": "e  os  crentes  não  podem  se  manter  no  amor"}, {"tStartMs": 1521560, "text": "de  Deus  sem  depender  dele  pedindo  ele  ou"}, {"tStartMs": 1525880, "text": "se  dirigindo  ao  Senhor  em  oração  o  amor"}, {"tStartMs": 1528310, "text": "a  Deus  não  pode  ser  sustentados  em  um"}, {"tStartMs": 1530230, "text": "relacionamento  com  ele  e  esse"}, {"tStartMs": 1532600, "text": "relacionamento  parte  dele  é  nutrido  pela"}, {"tStartMs": 1535720, "text": "oração"}, {"tStartMs": 1538440, "text": "e  espere  pela  misericórdia  de  Cristo  e"}, {"tStartMs": 1541259, "text": "aqui  algo  interessante  o  valor  de  quando"}, {"tStartMs": 1545279, "text": "nós  nos  aproximamos  a  da  língua  original"}, {"tStartMs": 1548179, "text": "viva  que  foi  escrita  o  antigo  testamento"}, {"tStartMs": 1550620, "text": "esperando  essa  palavra  No  grego  tem  a"}, {"tStartMs": 1552929, "text": "ideia  de  assistir  de  olhar  com"}, {"tStartMs": 1555529, "text": "expectativa  e  com  certeza  como  cristãos"}, {"tStartMs": 1559879, "text": "não  precisamos  nos  perguntar  Se  Jesus"}, {"tStartMs": 1563460, "text": "voltar  a  nós  temos  essa  plena  convicção"}, {"tStartMs": 1566159, "text": "de  que  ele  vai  voltar  então  uma  vida  que"}, {"tStartMs": 1569639, "text": "é  controlada  olhando  para  Eternidade  na"}, {"tStartMs": 1573659, "text": "expectativa  de  que  o  Senhor  Jesus  Cristo"}, {"tStartMs": 1575820, "text": "possa  voltar  hoje"}, {"tStartMs": 1577779, "text": "e  você  pensa  alguém  que  vive  Essa"}, {"tStartMs": 1580899, "text": "realidade"}, {"tStartMs": 1582450, "text": "é  alguém  que  possui  uma  caminhada  com  o"}, {"tStartMs": 1585750, "text": "senhor"}, {"tStartMs": 1587040, "text": "o  que  cresce  na  palavra  do  senhor  a  sua"}, {"tStartMs": 1591180, "text": "vida  é  moldada  por  uma  vida  de  oração  no"}, {"tStartMs": 1594990, "text": "espírito"}, {"tStartMs": 1597340, "text": "em  todo  esse  processo  vai  revelar  alguém"}, {"tStartMs": 1599920, "text": "que  anseia  pela  volta  de  Cristo"}, {"tStartMs": 1604620, "text": "os  seus  desejos  não  são  as  coisas  deste"}, {"tStartMs": 1607230, "text": "mundo"}, {"tStartMs": 1608890, "text": "e  ele  não  perde  tempo  com  as  coisas"}, {"tStartMs": 1611410, "text": "deste  mundo  e  certamente  irmãos  estão"}, {"tStartMs": 1613660, "text": "grande  desafio  para  nós"}, {"tStartMs": 1615549, "text": "e  a  nossa  inclinação"}, {"tStartMs": 1617940, "text": "e  por  vezes  a  mim  que  nação"}, {"tStartMs": 1621380, "text": "e  é  de  concentrar  a  atenção  o  esforço  em"}, {"tStartMs": 1624590, "text": "coisas  desta  terra"}, {"tStartMs": 1627500, "text": "é  mas  aquele  crente  maduro  aquele"}, {"tStartMs": 1630500, "text": "cliente  que  está  crescendo  tá"}, {"tStartMs": 1632890, "text": "perseverando  no  amor  de  Deus  é  alguém"}, {"tStartMs": 1636320, "text": "que  vive  olhando  para  frente  na"}, {"tStartMs": 1639400, "text": "expectativa  da  volta  do  Senhor  Jesus  a"}, {"tStartMs": 1643520, "text": "única  coisa  pela  qual  os  apostas  apostas"}, {"tStartMs": 1647150, "text": "apostas  roupa  podem  esperar  é  o"}, {"tStartMs": 1650390, "text": "julgamento  mas  o  povo  de  Deus  espera"}, {"tStartMs": 1652580, "text": "receber  Misericórdia  em  sua  misericórdia"}, {"tStartMs": 1655780, "text": "Deus  não  apenas  salvar  do  pecado  como"}, {"tStartMs": 1658640, "text": "também  livro  A  igreja  deste  mundo"}, {"tStartMs": 1661100, "text": "perverso"}, {"tStartMs": 1662890, "text": "bom  então  as  atitude  descreve  uma  vida"}, {"tStartMs": 1665950, "text": "motivada  pela  promessa  da  volta  do"}, {"tStartMs": 1669280, "text": "Senhor"}, {"tStartMs": 1671040, "text": "bom  e  sua  misericórdia  Jesus  voltará"}, {"tStartMs": 1674430, "text": "para  nos  buscar  e  nos  levar  para  junto"}, {"tStartMs": 1677400, "text": "de  si  essa  é  uma  realidade  é  só  uma"}, {"tStartMs": 1680340, "text": "esperança  firme  que  nós  temos  em  Cristo"}, {"tStartMs": 1682230, "text": "Jesus  Ele  Virá  nos  buscar"}, {"tStartMs": 1686460, "text": "e  queira  Deus  que  seja  hoje  não  por"}, {"tStartMs": 1689940, "text": "conta  da  pandemia  Não  por  conta  dos"}, {"tStartMs": 1693780, "text": "problemas  que  tenha  sediado  você  e  tem"}, {"tStartMs": 1696660, "text": "tiranizado  a  sua  paz"}, {"tStartMs": 1699399, "text": "se  alguém  que  ama  o  senhor  desejar"}, {"tStartMs": 1702759, "text": "ardentemente  a  presença  do  Senhor  e"}, {"tStartMs": 1706130, "text": "e  não  é  motivado  por  circunstâncias"}, {"tStartMs": 1708620, "text": "adversas"}, {"tStartMs": 1710130, "text": "é  mais  uma  Nelo  pela  presença  dele  ora"}, {"tStartMs": 1713640, "text": "vem  senhor  Jesus  ora  vem  senhor  Jesus  e"}, {"tStartMs": 1717810, "text": "terceiro  lugar  alcance  aqueles  afetados"}, {"tStartMs": 1721880, "text": "pelo  falso  ensino  portanto  seja"}, {"tStartMs": 1725250, "text": "misericordioso  com  aqueles  que  duvidam"}, {"tStartMs": 1728070, "text": "pode  haver  entre  nós  aqui  pessoas  que"}, {"tStartMs": 1730560, "text": "ação  novos  convertidos  e  quê  Porque  só"}, {"tStartMs": 1734250, "text": "novos  convertidos  eles  ainda  não  tem"}, {"tStartMs": 1737430, "text": "esse  discernimento  da  palavra  eles  podem"}, {"tStartMs": 1740310, "text": "ser  influenciáveis  pelo  falso  ensino"}, {"tStartMs": 1742920, "text": "seja  ele  dentro  da  igreja  seja  ele  a"}, {"tStartMs": 1746430, "text": "ministrado  fora  da  igreja"}, {"tStartMs": 1749789, "text": "bom  então  como  objeto  da  Misericórdia  de"}, {"tStartMs": 1752700, "text": "Cristo  devemos  estender  a  misericórdia"}, {"tStartMs": 1756289, "text": "aqueles  que  vacilão  com  a  verdade  do"}, {"tStartMs": 1759389, "text": "Evangelho  meus  irmãos  do  não  nós  não"}, {"tStartMs": 1762119, "text": "devemos  julgar  essas  pessoas  ou  primeira"}, {"tStartMs": 1765239, "text": "essas  pessoas"}, {"tStartMs": 1768310, "text": "e  antes  de  sermos  objetos  da"}, {"tStartMs": 1771250, "text": "misericórdia  do  Senhor  muitos  de  nós"}, {"tStartMs": 1774750, "text": "e  não  queríamos  nada  com  o  senhor"}, {"tStartMs": 1778240, "text": "Há  muitos  aqui  odiavam  os  crentes"}, {"tStartMs": 1783049, "text": "eu  não  tinha  amizade  com  os  crentes"}, {"tStartMs": 1785720, "text": "zombavam  dos  crentes"}, {"tStartMs": 1788200, "text": "bom  mas  um  dia  você  foi  objeto  do  amor"}, {"tStartMs": 1790419, "text": "de  Cristo  da  Misericórdia  dele  você  foi"}, {"tStartMs": 1792970, "text": "alcançado  alguém  pregou  o  evangelho  para"}, {"tStartMs": 1795100, "text": "você  e  o  Espírito  Santo  ágil  e  te  deu"}, {"tStartMs": 1799029, "text": "vida"}, {"tStartMs": 1800050, "text": "se  você  então  agora  é  chamado  ajudar"}, {"tStartMs": 1803590, "text": "essas  pessoas"}, {"tStartMs": 1805059, "text": "o  que  podem  ter  uma  conversão  genuína"}, {"tStartMs": 1807600, "text": "que  professar  uma  fé  genuína"}, {"tStartMs": 1810809, "text": "inicialmente  contudo  ainda  não  sou  uma"}, {"tStartMs": 1814450, "text": "duros  espiritualmente"}, {"tStartMs": 1816880, "text": "ó  e  aqui  eu  quero  deixar  um  desafio  para"}, {"tStartMs": 1819280, "text": "você  homem  mais  velho  mulher  mais  velha"}, {"tStartMs": 1822130, "text": "mais  madura"}, {"tStartMs": 1825370, "text": "nós  temos  pessoas  que  precisam  ser"}, {"tStartMs": 1827620, "text": "discipuladas  as"}, {"tStartMs": 1829660, "text": "E  aí  entre  nós  aqui  pessoas  que  precisam"}, {"tStartMs": 1832060, "text": "conhecer  e  crescer  na  graça  do  Senhor"}, {"tStartMs": 1836560, "text": "Jesus  Cristo"}, {"tStartMs": 1838720, "text": "e  como  nós  podemos  ter  uma  igreja  forte"}, {"tStartMs": 1842150, "text": "e  além  de  um  púlpito  forte"}, {"tStartMs": 1845630, "text": "os  homens  e  mulheres  maduros  ensinando"}, {"tStartMs": 1850240, "text": "outros"}, {"tStartMs": 1852330, "text": "e  a  crescer  e  no  conhecimento  do  Senhor"}, {"tStartMs": 1855679, "text": "mulheres  mais  idosas  ensinando  as  mais"}, {"tStartMs": 1859950, "text": "jovens"}, {"tStartMs": 1861810, "text": "os  homens  mais  maduros  homens  idosos"}, {"tStartMs": 1865550, "text": "ensinando  novos  convertidos  isso  uma"}, {"tStartMs": 1869760, "text": "marca  de  uma  igreja  saudável"}, {"tStartMs": 1872410, "text": "e  isso  é  o  zelo  pela  verdade  do  Senhor"}, {"tStartMs": 1877120, "text": "e  devemos  então  encorajar  e  apontar"}, {"tStartMs": 1880580, "text": "é  para  eles  Jesus  e  a  sua  suficiência"}, {"tStartMs": 1886169, "text": "o  que  nós  precisamos  é  de  uma  pessoa  é"}, {"tStartMs": 1890609, "text": "do  senhor  Jesus  e  tudo  que  nós"}, {"tStartMs": 1893220, "text": "precisamos  para  viver  uma  vida  que"}, {"tStartMs": 1895619, "text": "agrada  ele  encontramos  em  sua  palavra  e"}, {"tStartMs": 1897899, "text": "somente  nela"}, {"tStartMs": 1899399, "text": "bom  então  precisamos  manejá-la  bem"}, {"tStartMs": 1901759, "text": "Precisamos  conhecê-la  bem"}, {"tStartMs": 1904519, "text": "nós  precisamos  amar  a  palavra  que"}, {"tStartMs": 1908779, "text": "revelam  o  Deus  da  palavra"}, {"tStartMs": 1911630, "text": "e  isso  vai  ser  transbordado  em  desejo  de"}, {"tStartMs": 1917540, "text": "ensinar  outras  pessoas"}, {"tStartMs": 1921920, "text": "é  porque  aí  fora  infelizmente  vivemos"}, {"tStartMs": 1925040, "text": "uma  realidade  de  falsos  ensinamentos"}, {"tStartMs": 1929620, "text": "pessoas  que  sobe  no  púlpito  e  só  contam"}, {"tStartMs": 1932300, "text": "piadas"}, {"tStartMs": 1934780, "text": "o  desejo  apenas  de  entreter  pessoas  não"}, {"tStartMs": 1937840, "text": "a  doutrina  não  é  falado  nada  de  um"}, {"tStartMs": 1940480, "text": "Salvador  não  é  falado  nada  de  o  cão"}, {"tStartMs": 1944410, "text": "pecador  nós  somos  e  da  nossa  necessidade"}, {"tStartMs": 1947400, "text": "urgente  do  Perdão  de  Cristo"}, {"tStartMs": 1953290, "text": "Olá  seja  decisiva  com  aqueles  que  estão"}, {"tStartMs": 1956560, "text": "em  perigo  ou  seja  há  uma  urgência  aqui"}, {"tStartMs": 1960120, "text": "temos  três  grupos  aqui  que  Judas  lista"}, {"tStartMs": 1963070, "text": "para  nós  e  esse  é  o  segundo  grupo  alma"}, {"tStartMs": 1965680, "text": "uma  urgência  devemos  agir  rapidamente"}, {"tStartMs": 1968620, "text": "para  com  aqueles  que  ainda  podem  se"}, {"tStartMs": 1971320, "text": "arrepender  salvalaio  se  ao  termo  que  ele"}, {"tStartMs": 1974890, "text": "usa  como  se  aquele  Tição  estivesse"}, {"tStartMs": 1977350, "text": "dentro  do  fogo  agora  ele  é  tirado"}, {"tStartMs": 1979120, "text": "daquele  fogo"}, {"tStartMs": 1982260, "text": "é  a  única  forma  de  você  fazer  isso  é"}, {"tStartMs": 1985800, "text": "proclamando  o  evangelho"}, {"tStartMs": 1988940, "text": "e  trocando  o  evangelho"}, {"tStartMs": 1991200, "text": "e  se  envolva  com  pessoas"}, {"tStartMs": 1994060, "text": "e  se  aproxime  de  pessoas"}, {"tStartMs": 1997330, "text": "e  faça  essa  leitura"}, {"tStartMs": 2000110, "text": "é  de  pessoas"}, {"tStartMs": 2002919, "text": "o  e  pregue  o  evangelho  da  Glória  e  da"}, {"tStartMs": 2005559, "text": "Graça  de  Deus  para  essas  pessoas"}, {"tStartMs": 2010659, "text": "Olá  seja  cauteloso  com  aqueles  que  estão"}, {"tStartMs": 2013119, "text": "contaminados  E  se  o  terceiro  grupo  e  é"}, {"tStartMs": 2017019, "text": "uma  condição  mais  desesperadora  de  todas"}, {"tStartMs": 2020249, "text": "aqueles  que  abraçam  as  medidas  esses"}, {"tStartMs": 2022869, "text": "falsos  Mestres"}, {"tStartMs": 2025660, "text": "e  por  conta  da  daquilo  que  eles  ensinam"}, {"tStartMs": 2028360, "text": "é  conveniente  para  o  seu  estilo  de  vida"}, {"tStartMs": 2031390, "text": "pecaminoso"}, {"tStartMs": 2032669, "text": "e  o  pecado  então  manchou  E  contaminou"}, {"tStartMs": 2035279, "text": "essas  pessoas  qual  nosso  papel  amá-los"}, {"tStartMs": 2039109, "text": "ambyos  tem  misericórdia  mas  não  chegue"}, {"tStartMs": 2042899, "text": "muito  perto  pois  até  as  roupas  deles"}, {"tStartMs": 2045739, "text": "podem  contaminá-los  se  você  não  tomar"}, {"tStartMs": 2048510, "text": "cuidado"}, {"tStartMs": 2050820, "text": "e  aqui  talvez  a  ideia  de  que  para  ganhar"}, {"tStartMs": 2054600, "text": "a  um  certo  grupo  de  pessoas  Então  vou  me"}, {"tStartMs": 2058410, "text": "envolver  com  aquele  grupo  de  pessoas"}, {"tStartMs": 2060270, "text": "onde  é  muito  claro  o  estilo  de  vida"}, {"tStartMs": 2063660, "text": "pecaminoso  e  para  que  eu  possa  ganhar  os"}, {"tStartMs": 2066900, "text": "Então  vou  viver  aquele  estilo  de  vida"}, {"tStartMs": 2069150, "text": "pecaminoso"}, {"tStartMs": 2070870, "text": "e  eu  vou  praguejar  como  eles  praguejam"}, {"tStartMs": 2075559, "text": "e  para  ganhar  os  corruptos  você  não"}, {"tStartMs": 2077749, "text": "precisa  de  ver  como  um  corrupto"}, {"tStartMs": 2081200, "text": "e  para  ganhar  aqueles  que  a  dívidas"}, {"tStartMs": 2086679, "text": "libertinas  você  não  precisa  viver  uma"}, {"tStartMs": 2089149, "text": "vida  libertina  muito  pelo  contrário  nós"}, {"tStartMs": 2092419, "text": "somos  chamados  para  sermos  luz  e  sal"}, {"tStartMs": 2095980, "text": "para  este  mundo"}, {"tStartMs": 2099280, "text": "e  em  quarto  lugar  desfrute  da  segurança"}, {"tStartMs": 2103570, "text": "em  Cristo  Aqui  nós  temos  o  início  de"}, {"tStartMs": 2106870, "text": "algo  que  é  chamado  doxologia  e  a"}, {"tStartMs": 2109510, "text": "doxologia  ela  é  em  várias  epístolas  ela"}, {"tStartMs": 2113980, "text": "é  a  conclusão  de  uma  carta"}, {"tStartMs": 2116870, "text": "e  o  autor  então  depois  de  desenvolver  o"}, {"tStartMs": 2119420, "text": "seu  argumento  depois  dele  então"}, {"tStartMs": 2121490, "text": "comunicar  aquilo  pelo  qual  Espírito"}, {"tStartMs": 2123920, "text": "Santo  Deu  a  ele  para  comunicar  ele  agora"}, {"tStartMs": 2127040, "text": "faz  o  fechamento  dessa  carta  e  quando"}, {"tStartMs": 2130100, "text": "ele  se  lembra  de  do  Senhor  Jesus  Cristo"}, {"tStartMs": 2132200, "text": "da  pessoa  dele  quando  ele  se  lembra  de"}, {"tStartMs": 2135440, "text": "quem  deu  Zé  e  daquilo  que  ele  fez  por"}, {"tStartMs": 2137840, "text": "nós  ele  então  e  rompe  em  louvor  isso  a"}, {"tStartMs": 2142040, "text": "doxologia  ele  rompe  em  glória  ao  Senhor"}, {"tStartMs": 2147380, "text": "ele  quer  glorificar  o  Senhor  então  Judas"}, {"tStartMs": 2150740, "text": "faz  a  seguinte  forma  essa  segurança  que"}, {"tStartMs": 2153440, "text": "nós  temos  em  Cristo"}, {"tStartMs": 2155670, "text": "é  porque  Deus  é  Poderoso  Ele  É  Poderoso"}, {"tStartMs": 2158790, "text": "então  para  nos  preservar  porque  Deus  é"}, {"tStartMs": 2162030, "text": "perfeitamente  fiel  extremamente  poderoso"}, {"tStartMs": 2164220, "text": "infinitamente  amoroso  ele  não  permitirá"}, {"tStartMs": 2167250, "text": "que  seus  filhos  se  distanciam  da  Fé  da"}, {"tStartMs": 2170549, "text": "festa  Salvadora  de  modo  a  se  perder  e"}, {"tStartMs": 2173130, "text": "seus  pecados"}, {"tStartMs": 2174940, "text": "e  não  só  ele  está  disposto  a  preservar"}, {"tStartMs": 2178750, "text": "os  seus  ocasionalmente  antes  é  capaz  de"}, {"tStartMs": 2182260, "text": "preservá-los  até  o  fim  nós  cantamos  aqui"}, {"tStartMs": 2185790, "text": "que  somos  guardados  pelo  poder  de  Jesus"}, {"tStartMs": 2191569, "text": "Olá  meus  irmãos  foi  pago  um  alto  preço  e"}, {"tStartMs": 2195349, "text": "esse  preço  que  foi  pago  tão  alto"}, {"tStartMs": 2198289, "text": "e  é  capaz  de  nos  guardar  de  tropeçar  até"}, {"tStartMs": 2203689, "text": "o  fim"}, {"tStartMs": 2205230, "text": "e  até  que  a  morte  venha  nos  visitar  ou"}, {"tStartMs": 2209280, "text": "até  que  o  Senhor  Jesus  Cristo  volte"}, {"tStartMs": 2212670, "text": "a  hora  nos  proteger  não  de  proteger  de"}, {"tStartMs": 2217109, "text": "acidentes  de  dores  que  venhamos  a"}, {"tStartMs": 2220349, "text": "experimentar  aqui"}, {"tStartMs": 2223160, "text": "É  mas  ele  é  capaz  de  proteger  você  nessa"}, {"tStartMs": 2225830, "text": "vida  apesar  de  todos  os  perigos  e  os"}, {"tStartMs": 2228560, "text": "perigos  aqui  são  os  ataques  de  satanás"}, {"tStartMs": 2231100, "text": "os  ataques  de  uma  falsa  doutrina  ele  é"}, {"tStartMs": 2236570, "text": "poderoso  para  nos  guardar  nos  proteger"}, {"tStartMs": 2239569, "text": "e  lembre-se  você  foi  comprado  por  um"}, {"tStartMs": 2243680, "text": "preço  alto  que  Jesus  Cristo  não  vai"}, {"tStartMs": 2246739, "text": "falhar  em  perder  nenhum  dos  seus  eleitos"}, {"tStartMs": 2253190, "text": "e  por  isso  também  pode  salvar  totalmente"}, {"tStartMs": 2256730, "text": "os  que  chegam  a  Deus  vivendo  sempre  para"}, {"tStartMs": 2259160, "text": "interceder  por  ele"}, {"tStartMs": 2262119, "text": "nós  temos  um  sumo  sacerdote  que"}, {"tStartMs": 2264880, "text": "intercede  por  nós  constantemente  foi  ele"}, {"tStartMs": 2269440, "text": "quem  deu  a  sua  vida  foi  ele  que  derramou"}, {"tStartMs": 2271240, "text": "Seu  Precioso  Sangue  ele  não  falhará  em"}, {"tStartMs": 2275019, "text": "proteger  preservar  os  seus"}, {"tStartMs": 2278470, "text": "os  romanos  8:37  dizem  todas  essas  coisas"}, {"tStartMs": 2281710, "text": "porém  Somos  mais  que  vencedores  por  meio"}, {"tStartMs": 2284500, "text": "daquele  que  nos  amou  porque  eu  estou  bem"}, {"tStartMs": 2287230, "text": "certo  de  que  nem  a  morte  Nem  a  Vida  Nem"}, {"tStartMs": 2289270, "text": "os  anjos  nem  os  principados  nem  as"}, {"tStartMs": 2291760, "text": "coisas  do  presente  nem  do  porvir  nem  os"}, {"tStartMs": 2294730, "text": "poderes  nem  a  altura  nem  a  profundidade"}, {"tStartMs": 2297210, "text": "nem  qualquer  outra  criatura  poderá"}, {"tStartMs": 2300359, "text": "separar-nos  do  amor  de  Deus  que  está  em"}, {"tStartMs": 2303670, "text": "Cristo  Jesus  nosso  senhor  nada  incluindo"}, {"tStartMs": 2309340, "text": "atos  pessoais  de  Pecado  pode  separar  o"}, {"tStartMs": 2312940, "text": "verdadeiro  crente  do  seu  Salvador"}, {"tStartMs": 2316410, "text": "e  não  há  nada  não  pecado  que  nossa"}, {"tStartMs": 2319730, "text": "possamos  cometer"}, {"tStartMs": 2322890, "text": "o  que  nos  venha  a  nos  distanciarmos"}, {"tStartMs": 2326690, "text": "permanentemente  do  nosso  salvador"}, {"tStartMs": 2330560, "text": "o  Judas  está  irrompendo  em  louvor  quando"}, {"tStartMs": 2334400, "text": "ele  pensa  nessas  coisas"}, {"tStartMs": 2336369, "text": "Ah  e  não  consegue  se  conter"}, {"tStartMs": 2339550, "text": "e  nós  somos  guardados  e  preservados  Por"}, {"tStartMs": 2343480, "text": "que  Alguém  pagou  um  preço  altíssimo  e"}, {"tStartMs": 2345850, "text": "ele  é  poderoso  para  nos  guardar  até  o"}, {"tStartMs": 2349930, "text": "fim  da  nossa  jornada  ou  até  que  ele"}, {"tStartMs": 2353170, "text": "volte"}, {"tStartMs": 2356170, "text": "nós  estamos  Seguros  Na  promessa  de  Deus"}, {"tStartMs": 2360030, "text": "e  para  vermos  a  sua  glória  Veja  a  ser"}, {"tStartMs": 2364590, "text": "imaculado  que  é  o  texto  Diz  aqui  a"}, {"tStartMs": 2367110, "text": "significa  que  somos  sem  defeito"}, {"tStartMs": 2369870, "text": "irrepreensíveis  eu  agora  como  isso  se"}, {"tStartMs": 2373110, "text": "deu"}, {"tStartMs": 2374320, "text": "o  pastor  mas  nós  experimentamos  pecados"}, {"tStartMs": 2377430, "text": "nós  ainda  caímos  talvez  eu  tenho  até"}, {"tStartMs": 2381610, "text": "pecado  quando  você  ficou  um  tempo  aí"}, {"tStartMs": 2384430, "text": "procurando  o  PowerPoint  eu  fiquei  irado"}, {"tStartMs": 2387730, "text": "é  porque  pode  ser  que  atrás  e  o  culto"}, {"tStartMs": 2392770, "text": "bom  e  você  pegou"}, {"tStartMs": 2395230, "text": "e  eu  fiz  os  exercícios  para  não  pecar"}, {"tStartMs": 2397630, "text": "aqui"}, {"tStartMs": 2400000, "text": "O  que  quer  dizer  que  quando  Jesus  Cristo"}, {"tStartMs": 2404160, "text": "e  derramou  seu  sangue  e  foi  ressuscitado"}, {"tStartMs": 2406859, "text": "ao  terceiro  dia"}, {"tStartMs": 2409170, "text": "e  não  há  pecado  que  ele  não  possa"}, {"tStartMs": 2411059, "text": "perdoar"}, {"tStartMs": 2414320, "text": "e  quer  dizer  que  quando  nós  colocamos  a"}, {"tStartMs": 2417530, "text": "nossa  fé  EA  Nossa  confiança  no  Senhor"}, {"tStartMs": 2420290, "text": "Jesus  Cristo  ele  remove  as  nossas  Vestes"}, {"tStartMs": 2425150, "text": "manchadas  de  escremento  pelo  pecado  e"}, {"tStartMs": 2428810, "text": "nos  veste  com  novas  roupas"}, {"tStartMs": 2433500, "text": "e  somos  então  colocados  na  presença  de"}, {"tStartMs": 2436710, "text": "Deus  a  única  forma  de  termos  acesso  a"}, {"tStartMs": 2440460, "text": "presença  de  Deus  é  quando  nós  somos"}, {"tStartMs": 2443010, "text": "purificados"}, {"tStartMs": 2444849, "text": "e  pelo  sangue  do  Senhor  Jesus  Cristo"}, {"tStartMs": 2450930, "text": "e  ele  então  nos  impede  de  tropeçar  e  ele"}, {"tStartMs": 2454260, "text": "irá  nos  apresentar  sem  mancha  por  causa"}, {"tStartMs": 2457859, "text": "então  da  sua  promessa  de  completar  a"}, {"tStartMs": 2459990, "text": "nossa  salvação  veremos  a  sua  glória"}, {"tStartMs": 2464150, "text": "nós  estaremos  Face  a  Face  com  Deus"}, {"tStartMs": 2467770, "text": "estaremos  Face  a  Face  com  Cristo"}, {"tStartMs": 2471930, "text": "os  irmãos  se  isso  não  motivar  o  seu"}, {"tStartMs": 2474990, "text": "coração  a  feira  atraído  para  o  senhor"}, {"tStartMs": 2479790, "text": "se  você  precisa  Então  de  ter  o  seu"}, {"tStartMs": 2482070, "text": "coração  reaquecido  por  quem  o  senhor  é  e"}, {"tStartMs": 2487500, "text": "por  aquilo  que  ele  fez  por  você  na  cruz"}, {"tStartMs": 2490320, "text": "do  Calvário"}, {"tStartMs": 2493020, "text": "e  o  que  é  triste  é  que  talvez  no  coração"}, {"tStartMs": 2495660, "text": "de  muitos  um  desejo  enorme  de  que  o  seu"}, {"tStartMs": 2499740, "text": "irmão  acabe  para  que  ele  chega  em  casa  e"}, {"tStartMs": 2502800, "text": "possa  assistir  aquilo  que  confere  a  ele"}, {"tStartMs": 2505650, "text": "algum  tipo  de  prazer"}, {"tStartMs": 2507550, "text": "se  você  precisa  Então  reavaliar  o  que"}, {"tStartMs": 2510880, "text": "realmente  traz  prazer  para  você"}, {"tStartMs": 2515440, "text": "e  o  cliente  então  desejo  o  crente  que"}, {"tStartMs": 2518410, "text": "vive  uma  vida  no  espírito  que  é"}, {"tStartMs": 2520060, "text": "controlado  pelo  espírito  que"}, {"tStartMs": 2523200, "text": "constantemente  está  crescendo  no"}, {"tStartMs": 2525580, "text": "conhecimento  do  Senhor  ele  anseia  pela"}, {"tStartMs": 2528700, "text": "presença  do  Senhor"}, {"tStartMs": 2530940, "text": "e  ele  deseja  encontrar-se  com  seu"}, {"tStartMs": 2533460, "text": "Salvador"}, {"tStartMs": 2535020, "text": "e  nós  encontramos  nosso  Senhor  por  meio"}, {"tStartMs": 2537540, "text": "da  sua  palavra"}, {"tStartMs": 2539920, "text": "e  nós  encontramos  a  Cristo  quando  nós"}, {"tStartMs": 2542290, "text": "separamos  um  tempo  para  orar  a  sós  com"}, {"tStartMs": 2545049, "text": "ele"}, {"tStartMs": 2546070, "text": "E aí"}, {"tStartMs": 2547420, "text": "se  você  encontramos  o  senhor  em  nossa"}, {"tStartMs": 2549579, "text": "hora  silenciosa  mas  a  um  encontro"}, {"tStartMs": 2554650, "text": "o  que  o  seu  coração  e  o  meu  coração  deve"}, {"tStartMs": 2557290, "text": "se  arder  por  dentro  ver  a  face  do  Senhor"}, {"tStartMs": 2561430, "text": "Jesus"}, {"tStartMs": 2563260, "text": "o  Judas  e  rompe  nesse  desejo"}, {"tStartMs": 2566420, "text": "hei  de  ver  a  face  de  Cristo"}, {"tStartMs": 2570720, "text": "nós  estamos  Seguros  na  pessoa  de  Deus"}, {"tStartMs": 2573859, "text": "ele  é  soberano  Ele  é  o  único  Deus  o"}, {"tStartMs": 2577410, "text": "único  Senhor  único  soberano  A  quem  e  com"}, {"tStartMs": 2580500, "text": "quem  devemos  contar  e  prestar  contas  Ou"}, {"tStartMs": 2584220, "text": "seja  a  nossa  segurança  eterna  tem  sua"}, {"tStartMs": 2586349, "text": "origem  na  pessoa  e  no  caráter  de  Deus"}, {"tStartMs": 2590480, "text": "portanto  uma  compreensão  íntima  pessoal"}, {"tStartMs": 2593369, "text": "e  bíblica  de  Deus  nos  ajudará  em  nossa"}, {"tStartMs": 2596340, "text": "segurança  e  confirmar  a  nossa  confiança"}, {"tStartMs": 2599010, "text": "no  Senhor  de  guarda  e  salva"}, {"tStartMs": 2602330, "text": "completamente"}, {"tStartMs": 2603900, "text": "o  mesmo  que  você  caia  Jesus  Cristo  nunca"}, {"tStartMs": 2607440, "text": "falhou"}, {"tStartMs": 2608770, "text": "e  me  buscar  um  seu  eleito  que  caiu"}, {"tStartMs": 2612960, "text": "e  talvez  você  esteja  experimentando  uma"}, {"tStartMs": 2615450, "text": "realidade"}, {"tStartMs": 2617170, "text": "e  onde  um  filho  seu"}, {"tStartMs": 2620010, "text": "e  tenha  abandonado  a  fé"}, {"tStartMs": 2623340, "text": "e  se  encantou  com  as  coisas  deste  mundo"}, {"tStartMs": 2626270, "text": "duas  sério  desse  mundo"}, {"tStartMs": 2629519, "text": "Oi  filha  o  eleito  do  Senhor"}, {"tStartMs": 2632130, "text": "a  Jesus  Cristo  nunca  irá  perdendo  a"}, {"tStartMs": 2635970, "text": "segurança  EA  Certeza  da  Salvação  de"}, {"tStartMs": 2638610, "text": "alguém"}, {"tStartMs": 2639800, "text": "e  ela  é  segura  sabe  por  quê  Porque  ela"}, {"tStartMs": 2643100, "text": "não  depende  de  nós"}, {"tStartMs": 2645090, "text": "é  a  nossa  salvação  nunca  dependeu  de"}, {"tStartMs": 2649650, "text": "algo  em  nós  nunca  dependeu  da  nossa"}, {"tStartMs": 2651750, "text": "fidelidade  a  Jesus  fidelidade  a  a  fé  a"}, {"tStartMs": 2658200, "text": "nossa  salvação  é  uma  obra  do  senhor"}, {"tStartMs": 2659970, "text": "Jesus"}, {"tStartMs": 2661860, "text": "e  esse  ele  verdadeiramente  chamou  você"}, {"tStartMs": 2664940, "text": "ele  irá  aguardar  você  porque  ele  é  o"}, {"tStartMs": 2667980, "text": "único  Deus  é  o  único  senhor  é  o  soberano"}, {"tStartMs": 2670680, "text": "ele  é  o  nosso  salvador  ele  é  um  pai  e"}, {"tStartMs": 2674310, "text": "salvador  um  filho  Salvador  luz  espíritos"}, {"tStartMs": 2677100, "text": "Salvador"}, {"tStartMs": 2680380, "text": "nós  estamos  seguros  no  louvor  a  Deus"}, {"tStartMs": 2683190, "text": "louvo  por  sua  glória  eterna  e  glória  e"}, {"tStartMs": 2687640, "text": "honra  corretamente  atribuída  a  Deus  por"}, {"tStartMs": 2690640, "text": "quem  ele  é  e  pelo  que  delícia"}, {"tStartMs": 2694700, "text": "Qual  é  a  soma  dos  seus  atributos  e  a"}, {"tStartMs": 2697849, "text": "glória  de  Deus  quando  nós  passamos  a"}, {"tStartMs": 2701839, "text": "meditar  nessas  coisas"}, {"tStartMs": 2704230, "text": "e  a  militar  na  obra  do  senhor  na"}, {"tStartMs": 2707350, "text": "história  da  Redenção"}, {"tStartMs": 2709600, "text": "e  o  seu  amor  e  misericórdia  revelado"}, {"tStartMs": 2713650, "text": "e  a  Israel  a  nós  que  éramos  excluídos"}, {"tStartMs": 2718809, "text": "mas  fomos  reaproximado  SUS  e  somos"}, {"tStartMs": 2722740, "text": "chamados  de  filhos  todo  aquele  pecador"}, {"tStartMs": 2725859, "text": "arrependido"}, {"tStartMs": 2727869, "text": "e  essas  coisas  dos  leva  então  a"}, {"tStartMs": 2730029, "text": "glorificar  o  senhor  quando  nós  olhamos"}, {"tStartMs": 2732700, "text": "para  o  caráter  dele  Louvre  ou  por  Sua"}, {"tStartMs": 2735849, "text": "Majestade  é  a  sua  grandeza  sendo"}, {"tStartMs": 2739119, "text": "liberada  espalhada  por  toda  a  sua"}, {"tStartMs": 2741249, "text": "criação"}, {"tStartMs": 2745339, "text": "nós  estamos  Seguros"}, {"tStartMs": 2747380, "text": "e  esse  louvor  a  Deus  louvo  Então  por  seu"}, {"tStartMs": 2750769, "text": "domínio  e  esse  domínio  fora  de  seu"}, {"tStartMs": 2753140, "text": "controle  toda  sobre  toda  a  criação"}, {"tStartMs": 2756220, "text": "enquanto  eu  pensava  nessas  coisas  Óbvio"}, {"tStartMs": 2759970, "text": "Nossa  a  nos  lembramos  do  momento"}, {"tStartMs": 2762500, "text": "pandêmico  que  vivemos"}, {"tStartMs": 2765480, "text": "e  até  mesmo  debaixo  desse  momento  que"}, {"tStartMs": 2768390, "text": "estamos  experimentando  o  senhor  é"}, {"tStartMs": 2772740, "text": "poderoso  é  ele  quem  domina  ele  quem"}, {"tStartMs": 2776190, "text": "governa  nada  disso  fugiu  do  governo  do"}, {"tStartMs": 2780480, "text": "domínio  do  Senhor"}, {"tStartMs": 2783440, "text": "I  love  you  por  sua  autoridade  o  Nossa"}, {"tStartMs": 2787540, "text": "tradução  está  soberania  mas  a  palavra  no"}, {"tStartMs": 2791750, "text": "grego  Epson  Cia  e  ele  Sofia  é  autoridade"}, {"tStartMs": 2795140, "text": "e  é  o  direito  intrínseco  de  Deus  de"}, {"tStartMs": 2797839, "text": "governar  todas  as  coisas"}, {"tStartMs": 2800330, "text": "e  quando  nós  olhamos  para  evangelho  de"}, {"tStartMs": 2802370, "text": "Marcos  nós  vemos  muito  caro  ali  o  que  é"}, {"tStartMs": 2804470, "text": "autoridade"}, {"tStartMs": 2805660, "text": "E  ai  Jesus  Cristo  expulsando  demônios"}, {"tStartMs": 2808410, "text": "autoridade  deles  sobre  o  mundo"}, {"tStartMs": 2810549, "text": "Sobrenatural  é  Jesus  Cristo  acalmando"}, {"tStartMs": 2813849, "text": "uma  tempestade"}, {"tStartMs": 2815490, "text": "a  autoridade  dele  sobre  a  criação"}, {"tStartMs": 2819010, "text": "E  aí  Jesus  Cristo  interpretando  a"}, {"tStartMs": 2821920, "text": "palavra"}, {"tStartMs": 2823230, "text": "e  ele  autoridade  Suprema  ele  é  a  palavra"}, {"tStartMs": 2830309, "text": "a  ver  já  altas  autoridades  de  Deus"}, {"tStartMs": 2834539, "text": "significa  que  o  mundo  não  está  indo  bem"}, {"tStartMs": 2836640, "text": "ou  mal  Fora  de  Controle  em  um  curso  sem"}, {"tStartMs": 2840900, "text": "direção  sem  ninguém  no  comando  a"}, {"tStartMs": 2844559, "text": "extinção  humana"}, {"tStartMs": 2846280, "text": "e  não  é  uma  possibilidade  porque  ele  tem"}, {"tStartMs": 2849430, "text": "todas  as  coisas  em  suas  mãos  Aniquilação"}, {"tStartMs": 2853540, "text": "nuclear  não  é  uma  possibilidade  porque"}, {"tStartMs": 2857020, "text": "ele  tem  todas  as  coisas  em  suas  mãos"}, {"tStartMs": 2861200, "text": "e  a  falha  na  evangelização  não  é  uma"}, {"tStartMs": 2864650, "text": "possibilidade  porque  ele  tem  todas  as"}, {"tStartMs": 2867290, "text": "coisas  em  suas  mãos  o  fracasso"}, {"tStartMs": 2870109, "text": "Missionário  Não  é  uma  possibilidade"}, {"tStartMs": 2871930, "text": "porque  ele  tem  todas  as  coisas  em  sua  em"}, {"tStartMs": 2874820, "text": "suas  mãos  perder  minha  salvação  não  é"}, {"tStartMs": 2878420, "text": "uma  possibilidade  porque  ele  tem  todas"}, {"tStartMs": 2881630, "text": "as  coisas  inclusive  eu  e  você  em  suas"}, {"tStartMs": 2885859, "text": "mãos"}, {"tStartMs": 2888680, "text": "e  nós  terminamos  então  aqui  a  epístola"}, {"tStartMs": 2891260, "text": "de  Judas  sendo  lembrados  de  que  somos"}, {"tStartMs": 2895160, "text": "guardados  pelo  poder  do  Senhor"}, {"tStartMs": 2899290, "text": "é  de  que  nada  nem  ninguém  pode  tirar  a"}, {"tStartMs": 2903790, "text": "nossa  salvação  que  Cristo  conquistou  na"}, {"tStartMs": 2905950, "text": "cruz  e  aquele  sacrifício  não  foi  em  vão"}, {"tStartMs": 2911470, "text": "nós  somos  lembrados  de  que  a  fé  deve  ser"}, {"tStartMs": 2914740, "text": "batalhada  deve  ser  defendida  ela  deve"}, {"tStartMs": 2919270, "text": "ser  a  cuidada  para  que  falsos  ensinos"}, {"tStartMs": 2923850, "text": "e  não  venham  a  nos  afastado  nosso  Senhor"}, {"tStartMs": 2928260, "text": "e  da  Verdade  do  Evangelho"}, {"tStartMs": 2930700, "text": "nós  somos  lembrados  de  que  a  única"}, {"tStartMs": 2933700, "text": "verdade  que  encontramos"}, {"tStartMs": 2935530, "text": "e  a  nossa  escrituras  que  revela  Deus  que"}, {"tStartMs": 2939850, "text": "revelam  o  senhor  de  revela  quem  nós"}, {"tStartMs": 2942250, "text": "somos  e  a  esperança  que  temos  em  Jesus"}, {"tStartMs": 2945150, "text": "que  revela  que  Jesus  é  suficiente"}, {"tStartMs": 2949200, "text": "e  portanto  os  cristãos  que  são  guardados"}, {"tStartMs": 2954030, "text": "pelo  poder  de  Deus  são  chamados  a"}, {"tStartMs": 2956099, "text": "crescer  em  maturidade  espiritual  zelando"}, {"tStartMs": 2959220, "text": "pela  fé  verdadeira  para  o  louvor  da"}, {"tStartMs": 2961859, "text": "Glória  de  Deus  vamos  orar"}, {"tStartMs": 2965200, "text": "o  senhor  nós  queremos  reconhecer  o  pai"}, {"tStartMs": 2968970, "text": "que  diante  de  tão  grande  salvação"}, {"tStartMs": 2972549, "text": "o  Judas  estava  disposto  a  escrever  e  sua"}, {"tStartMs": 2977019, "text": "graça  e  misericórdia  o  senhor  morreu"}, {"tStartMs": 2981119, "text": "e  a  nos  informar  e  anúncios  exortar"}, {"tStartMs": 2985339, "text": "e  a  vivermos  uma  vida  que  exala  quem  é  o"}, {"tStartMs": 2990349, "text": "senhor  uma  vida  a  Deus  voltar  da"}, {"tStartMs": 2993950, "text": "batalhar  pela  fé  por  esse  conjunto  de"}, {"tStartMs": 2997519, "text": "doutrinas  conjunto  ahn  da  Verdade"}, {"tStartMs": 3000849, "text": "Revelada  na  tua  palavra"}, {"tStartMs": 3002980, "text": "e  a  Batalha  pelo  evangelho  e  uma  batalha"}, {"tStartMs": 3006609, "text": "Deus  onde  nós  somos  alistados  debaixo  de"}, {"tStartMs": 3010720, "text": "uma  bandeira  em  que  temos  a  convicção"}, {"tStartMs": 3013440, "text": "dada  pelo  senhor  que  nenhum  desses"}, {"tStartMs": 3016840, "text": "soldados  se  perderá  a"}, {"tStartMs": 3019859, "text": "o  que  não  ao  Deus"}, {"tStartMs": 3022299, "text": "é  uma  batalha  Perdida  para  nós  que"}, {"tStartMs": 3026259, "text": "venhamos  a  sermos  perdidos  porque  o"}, {"tStartMs": 3031390, "text": "Senhor  conquistou  na  cruz  do  Calvário"}, {"tStartMs": 3033359, "text": "esse  poder  de  nos  guardar  até  o  fim"}, {"tStartMs": 3037049, "text": "portanto  ao  pai"}, {"tStartMs": 3039330, "text": "eu  posso  queremos  louvar  o  Senhor"}, {"tStartMs": 3041630, "text": "reconhecer  a  Sua  Majestade  a  tua  glória"}, {"tStartMs": 3045200, "text": "a  tua  soberania  o  teu  domínio  sobre  tudo"}, {"tStartMs": 3049470, "text": "e  sobre  todos"}, {"tStartMs": 3051210, "text": "o  E  pedimos  a  Deus  que  foi  nos  conceda  a"}, {"tStartMs": 3053580, "text": "graça"}, {"tStartMs": 3055180, "text": "é  de  executar  mos  o  nosso  papel  de"}, {"tStartMs": 3058599, "text": "proclamar  nos  Evangelhos  para  aqueles"}, {"tStartMs": 3060490, "text": "que  não  conhecem"}, {"tStartMs": 3061990, "text": "é  de  proclamarmos  o  evangelho  para"}, {"tStartMs": 3064330, "text": "aqueles  que  estão  fracos  que  ainda  estão"}, {"tStartMs": 3067000, "text": "na  dúvida  e  exercermos  amor  e"}, {"tStartMs": 3070510, "text": "misericórdia  por  aqueles  que  de  alguma"}, {"tStartMs": 3073210, "text": "forma  em  algum  momento  foram  assediados"}, {"tStartMs": 3076360, "text": "por  esses  ensinos"}, {"tStartMs": 3078109, "text": "e  dá-nos  a  Graça  a  Deus  e  sermos  fiéis"}, {"tStartMs": 3080869, "text": "ao  Senhor  fiéis  a  tua  verdade  a  verdade"}, {"tStartMs": 3085369, "text": "de  Deus  a  verdade  do  Evangelho"}, {"tStartMs": 3088310, "text": "a  nossa  igreja  Pai  venha  cumprir"}, {"tStartMs": 3090650, "text": "cabalmente  o  seu  papel  para  Glória  e"}, {"tStartMs": 3093980, "text": "Honra  do  Senhor  Jesus  Cristo  e  era  o"}, {"tStartMs": 3096620, "text": "nome  dele  que  eu  olho  e  agradeço  amém"}], "id": "g4lJ9mkq7Lw"}